powechi/__init__.py
powechi/core.py
powechi-0.1.0.dist-info/licenses/LICENSE
tests/__init__.py
tests/test_core.py
powechi-0.1.0.dist-info/METADATA
powechi-0.1.0.dist-info/WHEEL
powechi-0.1.0.dist-info/top_level.txt
powechi-0.1.0.dist-info/RECORD
