Metadata-Version: 2.4
Name: powechi
Version: 0.1.0
Summary: A powerful Python library for various utilities
Home-page: https://github.com/williamxiewz/powechi
Author: williamxiewz
Author-email: williamxiewz <williamxiewz@gmail.com>
License: MIT
Project-URL: Homepage, https://github.com/williamxiewz/powechi
Project-URL: Repository, https://github.com/williamxiewz/powechi
Project-URL: Issues, https://github.com/williamxiewz/powechi/issues
Keywords: utility,tools,python
Classifier: Development Status :: 3 - Alpha
Classifier: Intended Audience :: Developers
Classifier: License :: OSI Approved :: MIT License
Classifier: Operating System :: OS Independent
Classifier: Programming Language :: Python :: 3
Classifier: Programming Language :: Python :: 3.7
Classifier: Programming Language :: Python :: 3.8
Classifier: Programming Language :: Python :: 3.9
Classifier: Programming Language :: Python :: 3.10
Classifier: Programming Language :: Python :: 3.11
Requires-Python: >=3.10
License-File: LICENSE
Provides-Extra: dev
Requires-Dist: pytest>=6.0; extra == "dev"
Requires-Dist: black>=21.0; extra == "dev"
Requires-Dist: flake8>=3.8; extra == "dev"
Requires-Dist: mypy>=0.812; extra == "dev"
Requires-Dist: twine>=4.0; extra == "dev"
Requires-Dist: build>=0.8; extra == "dev"
Dynamic: author
Dynamic: home-page
Dynamic: license-file
Dynamic: requires-python
